{
    "GREENHOUSE_ID": 12,
    "TEMPERATURE": 29.5,
    "HUMIDITY": 0.87,
    "CO2": 33.2,
    "SUNLIGHT": 0.76,
    "START_DATETIME": "2023-02-26 19:08:35",
    "measurements": [
        [
            20,
            37.2,
            603,
            0.86
        ],
        [
            20,
            13.8,
            2238,
            0.96
        ],
        [
            20,
            28.7,
            1085,
            0.65
        ],
        [
            20,
            30.8,
            1608,
            0.62
        ],
        [
            20,
            16.7,
            1258,
            0.86
        ],
        [
            20,
            10.3,
            2630,
            0.8
        ],
        [
            31,
            21.0,
            425,
            0.94
        ],
        [
            31,
            36.2,
            1710,
            0.99
        ],
        [
            31,
            27.8,
            2046,
            0.69
        ],
        [
            31,
            34.6,
            1572,
            0.94
        ],
        [
            31,
            9.0,
            1713,
            0.98
        ],
        [
            31,
            11.2,
            728,
            0.75
        ],
        [
            41,
            19.4,
            2129,
            0.84
        ],
        [
            41,
            28.4,
            2027,
            0.64
        ],
        [
            41,
            30.9,
            2835,
            0.66
        ],
        [
            41,
            22.5,
            935,
            0.66
        ],
        [
            41,
            14.1,
            2650,
            0.78
        ],
        [
            41,
            33.1,
            1809,
            0.96
        ],
        [
            51,
            26.8,
            2329,
            0.91
        ],
        [
            51,
            29.7,
            2212,
            0.61
        ],
        [
            51,
            25.5,
            1901,
            0.75
        ],
        [
            51,
            9.1,
            2650,
            0.81
        ],
        [
            51,
            21.2,
            2583,
            1.0
        ],
        [
            51,
            17.2,
            1770,
            1.0
        ],
        [
            69,
            34.9,
            2328,
            0.83
        ],
        [
            69,
            18.4,
            1057,
            0.73
        ],
        [
            69,
            22.9,
            2753,
            0.76
        ],
        [
            69,
            16.3,
            1583,
            0.75
        ],
        [
            69,
            9.1,
            995,
            0.63
        ],
        [
            69,
            18.8,
            441,
            0.66
        ],
        [
            81,
            37.3,
            1471,
            0.65
        ],
        [
            81,
            21.4,
            566,
            0.7
        ],
        [
            81,
            28.4,
            1879,
            0.99
        ],
        [
            81,
            31.8,
            2698,
            0.85
        ],
        [
            81,
            21.9,
            2140,
            0.83
        ],
        [
            81,
            10.2,
            2073,
            0.99
        ],
        [
            95,
            26.3,
            1472,
            0.88
        ],
        [
            95,
            9.0,
            444,
            0.82
        ],
        [
            95,
            35.4,
            2809,
            0.91
        ],
        [
            95,
            18.3,
            2180,
            0.95
        ],
        [
            95,
            18.8,
            2858,
            0.78
        ],
        [
            95,
            27.2,
            617,
            0.87
        ],
        [
            112,
            26.1,
            1554,
            0.95
        ],
        [
            112,
            19.2,
            2628,
            1.0
        ],
        [
            112,
            29.4,
            2883,
            0.61
        ],
        [
            112,
            8.2,
            2310,
            0.8
        ],
        [
            112,
            8.8,
            1225,
            0.87
        ],
        [
            112,
            16.4,
            2294,
            0.84
        ],
        [
            126,
            17.4,
            2852,
            0.74
        ],
        [
            126,
            14.8,
            1302,
            0.74
        ],
        [
            126,
            11.7,
            1987,
            0.61
        ],
        [
            126,
            28.4,
            1669,
            0.69
        ],
        [
            126,
            20.8,
            570,
            0.67
        ],
        [
            126,
            14.8,
            2072,
            0.95
        ],
        [
            137,
            36.6,
            1209,
            0.66
        ],
        [
            137,
            25.0,
            2511,
            0.96
        ],
        [
            137,
            33.1,
            804,
            0.83
        ],
        [
            137,
            15.5,
            2144,
            0.81
        ],
        [
            137,
            30.6,
            1807,
            0.76
        ],
        [
            137,
            27.2,
            2308,
            0.62
        ],
        [
            156,
            26.8,
            653,
            0.7
        ],
        [
            156,
            10.7,
            1003,
            0.68
        ],
        [
            156,
            14.9,
            970,
            0.61
        ],
        [
            156,
            22.5,
            2244,
            0.78
        ],
        [
            156,
            21.1,
            1457,
            0.87
        ],
        [
            156,
            37.3,
            1448,
            0.7
        ],
        [
            172,
            17.4,
            1444,
            0.64
        ],
        [
            172,
            21.3,
            2572,
            0.64
        ],
        [
            172,
            19.4,
            716,
            0.93
        ],
        [
            172,
            21.1,
            1262,
            0.93
        ],
        [
            172,
            32.2,
            1989,
            0.69
        ],
        [
            172,
            9.2,
            763,
            0.78
        ]
    ]
}